jupyterlab_citation_manager/__init__.py
jupyterlab_citation_manager/_version.py
jupyterlab_citation_manager/handlers.py
jupyterlab_citation_manager/styles.py
jupyterlab_citation_manager/tests/__init__.py
jupyterlab_citation_manager/tests/test_styles.py
jupyterlab_citation_manager/tests/resources/apa.csl
jupyterlab_citation_manager-1.0.0.data/data/etc/jupyter/jupyter_server_config.d/jupyterlab_citation_manager.json
jupyterlab_citation_manager-1.0.0.data/data/share/jupyter/labextensions/jupyterlab-citation-manager/package.json
jupyterlab_citation_manager-1.0.0.data/data/share/jupyter/labextensions/jupyterlab-citation-manager/schemas/jupyterlab-citation-manager/package.json.orig
jupyterlab_citation_manager-1.0.0.data/data/share/jupyter/labextensions/jupyterlab-citation-manager/schemas/jupyterlab-citation-manager/plugin.json
jupyterlab_citation_manager-1.0.0.data/data/share/jupyter/labextensions/jupyterlab-citation-manager/schemas/jupyterlab-citation-manager/zotero.json
jupyterlab_citation_manager-1.0.0.data/data/share/jupyter/labextensions/jupyterlab-citation-manager/static/109.79c476102289d10ba9b4.js
jupyterlab_citation_manager-1.0.0.data/data/share/jupyter/labextensions/jupyterlab-citation-manager/static/308.4666ad36b47acd0a274d.js
jupyterlab_citation_manager-1.0.0.data/data/share/jupyter/labextensions/jupyterlab-citation-manager/static/33.2b66053eaff0db65ac34.js
jupyterlab_citation_manager-1.0.0.data/data/share/jupyter/labextensions/jupyterlab-citation-manager/static/747.71495b70a33992ba4152.js
jupyterlab_citation_manager-1.0.0.data/data/share/jupyter/labextensions/jupyterlab-citation-manager/static/remoteEntry.b7109814a704cda38d4d.js
jupyterlab_citation_manager-1.0.0.data/data/share/jupyter/labextensions/jupyterlab-citation-manager/static/style.js
jupyterlab_citation_manager-1.0.0.data/data/share/jupyter/labextensions/jupyterlab-citation-manager/static/third-party-licenses.json
jupyterlab_citation_manager-1.0.0.dist-info/METADATA
jupyterlab_citation_manager-1.0.0.dist-info/WHEEL
jupyterlab_citation_manager-1.0.0.dist-info/licenses/LICENSE
jupyterlab_citation_manager-1.0.0.dist-info/RECORD
